xpiz/__init__.py
xpiz/__main__.py
xpiz/cli.py
xpiz-0.1.7.dist-info/LICENSE
xpiz-0.1.7.dist-info/METADATA
xpiz-0.1.7.dist-info/WHEEL
xpiz-0.1.7.dist-info/entry_points.txt
xpiz-0.1.7.dist-info/top_level.txt
xpiz-0.1.7.dist-info/RECORD
